{
  "totalFound": 75,
  "byDay": {
    "day1": 12,
    "day2": 35,
    "day3": 28
  },
  "sessions": [
    {
      "day": "Day 1",
      "date": "October 14, 2025",
      "title": "Monetization Strategies for Insurtechs",
      "startTime": "2025-10-14T09:00:00",
      "endTime": "2025-10-14T10:00:00",
      "location": "Main Stage",
      "track": "Strategy",
      "description": "Monetization is one of the biggest challenges for insurtechs and insurance service providers at every stage of growth. From early-stage startups struggling to price their first offering to established companies looking to optimize revenue streams.",
      "type": "Panel",
      "speakers": []
    },
    {
      "day": "Day 1",
      "date": "October 14, 2025",
      "title": "Insurance Leaders Summit",
      "startTime": "2025-10-14T10:00:00",
      "endTime": "2025-10-14T11:00:00",
      "location": "Main Stage",
      "track": "Leadership",
      "description": "Insurance leaders: the cards are on the table. Amid rising premiums, decreasing customer satisfaction, and tightening regulations – the cost of doing business is skyrocketing.",
      "type": "Summit",
      "speakers": []
    },
    {
      "day": "Day 1",
      "date": "October 14, 2025",
      "title": "AI-Powered Underwriting and Agentic Automation",
      "startTime": "2025-10-14T11:00:00",
      "endTime": "2025-10-14T12:00:00",
      "location": "Technology Track",
      "track": "Technology",
      "description": "Discover how leading insurers are transforming their operations through AI-powered underwriting, agentic automation across the policy lifecycle, and strategic legacy technology modernization.",
      "type": "Workshop",
      "speakers": []
    },
    {
      "day": "Day 1",
      "date": "October 14, 2025",
      "title": "Performance Marketing for Insurance Growth",
      "startTime": "2025-10-14T13:00:00",
      "endTime": "2025-10-14T14:00:00",
      "location": "Distribution Track",
      "track": "Distribution",
      "description": "Performance marketing is the main lever for increasing your book of business. But it's daunting. What works, what doesn't? We identify simple things you can be doing to give you an edge.",
      "type": "Workshop",
      "speakers": []
    },
    {
      "day": "Day 1",
      "date": "October 14, 2025",
      "title": "Wholesale Distribution Tech Revolution",
      "startTime": "2025-10-14T14:00:00",
      "endTime": "2025-10-14T15:00:00",
      "location": "Distribution Track",
      "track": "Distribution",
      "description": "Is wholesale distribution finally having its tech moment? Explore how wholesale brokers, MGAs, and capacity providers are using AI-driven tools to enable smarter decision-making.",
      "type": "Panel",
      "speakers": []
    },
    {
      "day": "Day 1",
      "date": "October 14, 2025",
      "title": "Corporate Development Summit",
      "startTime": "2025-10-14T15:00:00",
      "endTime": "2025-10-14T16:00:00",
      "location": "Executive Track",
      "track": "Strategy",
      "description": "Designed exclusively for corporate development, strategy, and innovation executives, this summit explores key insurance industry trends, including macroeconomic shifts, strategic M&A.",
      "type": "Summit",
      "speakers": []
    },
    {
      "day": "Day 1",
      "date": "October 14, 2025",
      "title": "State Farm Startup Pitch Competition",
      "startTime": "2025-10-14T16:00:00",
      "endTime": "2025-10-14T17:30:00",
      "location": "Main Stage",
      "track": "Innovation",
      "description": "Join us for the fourth annual State Farm Startup Pitch Competition. Launched in 2022, the competition highlights groundbreaking innovation in insurtech.",
      "type": "Competition",
      "speakers": []
    },
    {
      "day": "Day 1",
      "date": "October 14, 2025",
      "title": "Specialty Lines Innovation",
      "startTime": "2025-10-14T16:00:00",
      "endTime": "2025-10-14T17:00:00",
      "location": "Specialty Track",
      "track": "Specialty",
      "description": "Specialty lines are no longer a niche, they're the frontier. As risks evolve and clients demand more nuanced coverage, brokers have a golden opportunity to lead with expertise.",
      "type": "Panel",
      "speakers": []
    },
    {
      "day": "Day 1",
      "date": "October 14, 2025",
      "title": "Opening Night Reception",
      "startTime": "2025-10-14T18:00:00",
      "endTime": "2025-10-14T20:00:00",
      "location": "Expo Hall",
      "track": "Networking",
      "description": "Where innovation takes center stage and connections begin to spark! Join us for the evening as we kickoff ITC Vegas with our opening night reception!",
      "type": "Networking",
      "speakers": []
    },
    {
      "day": "Day 1",
      "date": "October 14, 2025",
      "title": "First Timers Expo Tour",
      "startTime": "2025-10-14T17:30:00",
      "endTime": "2025-10-14T18:00:00",
      "location": "Expo Floor",
      "track": "Orientation",
      "description": "First Timers, this one is for you! Join the ITC Vegas team for an exclusive tour of the Expo Floor.",
      "type": "Tour",
      "speakers": []
    },
    {
      "day": "Day 2",
      "date": "October 15, 2025",
      "title": "Expo Floor Opens",
      "startTime": "2025-10-15T08:00:00",
      "endTime": "2025-10-15T18:00:00",
      "location": "Expo Floor",
      "track": "Expo",
      "description": "The Expo Floor is your realm of innovation, where you'll connect with industry leaders, explore cutting-edge solutions, and form valuable partnerships.",
      "type": "Expo",
      "speakers": []
    },
    {
      "day": "Day 2",
      "date": "October 15, 2025",
      "title": "Climate Volatility and Property Risk",
      "startTime": "2025-10-15T09:00:00",
      "endTime": "2025-10-15T09:45:00",
      "location": "Main Stage",
      "track": "Property",
      "description": "As climate volatility increases and property risks become more complex, insurers are under pressure to respond faster, act smarter, and deliver more consistent outcomes.",
      "type": "Keynote",
      "speakers": []
    },
    {
      "day": "Day 2",
      "date": "October 15, 2025",
      "title": "Personalized Insurance with AI",
      "startTime": "2025-10-15T09:00:00",
      "endTime": "2025-10-15T09:45:00",
      "location": "Technology Track",
      "track": "Technology",
      "description": "Customers are no longer satisfied with generic policies and cookie-cutter service. They expect insurance tailored to their needs, behaviors, and risks—in real time.",
      "type": "Panel",
      "speakers": []
    },
    {
      "day": "Day 2",
      "date": "October 15, 2025",
      "title": "Battle for Direct Customer Access",
      "startTime": "2025-10-15T10:00:00",
      "endTime": "2025-10-15T10:45:00",
      "location": "Distribution Track",
      "track": "Distribution",
      "description": "Insurers, brokers, MGAs, insurtechs, and even big tech companies are all vying for the same thing: direct access to the customer.",
      "type": "Panel",
      "speakers": []
    },
    {
      "day": "Day 2",
      "date": "October 15, 2025",
      "title": "High-Volume Claims and Fraud",
      "startTime": "2025-10-15T10:00:00",
      "endTime": "2025-10-15T10:45:00",
      "location": "Claims Track",
      "track": "Claims",
      "description": "Claim leaders for high-volume carriers face an impossible math problem: tens of thousands of open injury claims, growing fraud exposure, and not nearly enough resources.",
      "type": "Workshop",
      "speakers": []
    },
    {
      "day": "Day 2",
      "date": "October 15, 2025",
      "title": "Zywave's Agentic AI Demo",
      "startTime": "2025-10-15T11:00:00",
      "endTime": "2025-10-15T11:30:00",
      "location": "Demo Theater",
      "track": "Technology",
      "description": "Zywave's Agentic AI workflows elevate insurance operations, enhance decision-making with real-time data, and foster seamless collaboration.",
      "type": "Demo",
      "speakers": []
    },
    {
      "day": "Day 2",
      "date": "October 15, 2025",
      "title": "Insurance Data Network and AI Against Fraud",
      "startTime": "2025-10-15T11:00:00",
      "endTime": "2025-10-15T11:45:00",
      "location": "Claims Track",
      "track": "Claims",
      "description": "In an era when fraud costs the P&C insurance industry nearly $122 billion annually, leveraging shared data and advanced AI technologies is critical.",
      "type": "Panel",
      "speakers": []
    },
    {
      "day": "Day 2",
      "date": "October 15, 2025",
      "title": "Commercial Insurance Revolution",
      "startTime": "2025-10-15T11:00:00",
      "endTime": "2025-10-15T11:45:00",
      "location": "Commercial Track",
      "track": "Commercial",
      "description": "For years, billions have flowed into insurtech, yet commercial insurance remained a fortress of complexity. But now, the barriers are cracking.",
      "type": "Keynote",
      "speakers": []
    },
    {
      "day": "Day 2",
      "date": "October 15, 2025",
      "title": "Multi-Cancer Early Detection Impact",
      "startTime": "2025-10-15T11:00:00",
      "endTime": "2025-10-15T11:45:00",
      "location": "Health Track",
      "track": "Health",
      "description": "Early detection of cancer has the potential to radically reshape healthcare costs, outcomes, and insurance models.",
      "type": "Panel",
      "speakers": []
    },
    {
      "day": "Day 2",
      "date": "October 15, 2025",
      "title": "Workday for Insurance Demo",
      "startTime": "2025-10-15T11:30:00",
      "endTime": "2025-10-15T12:00:00",
      "location": "Demo Theater",
      "track": "Technology",
      "description": "Workday is a leading enterprise platform that helps organizations manage their most important assets – their people and money.",
      "type": "Demo",
      "speakers": []
    },
    {
      "day": "Day 2",
      "date": "October 15, 2025",
      "title": "Convergence of Health and Wealth",
      "startTime": "2025-10-15T12:00:00",
      "endTime": "2025-10-15T12:45:00",
      "location": "Benefits Track",
      "track": "Benefits",
      "description": "Group benefits, life and annuities and health coverage were built for a fragmented past. But in today's world, where health affects wealth, jobs affect longevity and wellbeing is a lifelong journey.",
      "type": "Panel",
      "speakers": []
    },
    {
      "day": "Day 2",
      "date": "October 15, 2025",
      "title": "Big Tech's Insurance Invasion",
      "startTime": "2025-10-15T12:00:00",
      "endTime": "2025-10-15T12:45:00",
      "location": "Main Stage",
      "track": "Strategy",
      "description": "Big Tech is no longer circling insurance—it's making its move. From Amazon's embedded protections to Google's AI-driven risk models and Apple's health data integrations.",
      "type": "Keynote",
      "speakers": []
    },
    {
      "day": "Day 2",
      "date": "October 15, 2025",
      "title": "Claims Innovation Fireside Chat",
      "startTime": "2025-10-15T13:00:00",
      "endTime": "2025-10-15T13:30:00",
      "location": "Claims Track",
      "track": "Claims",
      "description": "A long, frustrating claims process is no longer acceptable in a world where consumers expect instant gratification.",
      "type": "Fireside Chat",
      "speakers": []
    },
    {
      "day": "Day 2",
      "date": "October 15, 2025",
      "title": "Agentic AI in Commercial Insurance",
      "startTime": "2025-10-15T13:00:00",
      "endTime": "2025-10-15T13:45:00",
      "location": "Commercial Track",
      "track": "Commercial",
      "description": "AI agents are gaining momentum across industries, but what does this mean for the complex, relationship-centric commercial insurance space?",
      "type": "Panel",
      "speakers": []
    },
    {
      "day": "Day 2",
      "date": "October 15, 2025",
      "title": "AI Arms Race in Fraud Detection",
      "startTime": "2025-10-15T13:00:00",
      "endTime": "2025-10-15T13:45:00",
      "location": "Claims Track",
      "track": "Claims",
      "description": "Fraudsters are evolving faster than ever, using deepfakes and AI-generated evidence to manipulate claims.",
      "type": "Panel",
      "speakers": []
    },
    {
      "day": "Day 2",
      "date": "October 15, 2025",
      "title": "Future of Actuaries in AI Era",
      "startTime": "2025-10-15T14:00:00",
      "endTime": "2025-10-15T14:45:00",
      "location": "Technology Track",
      "track": "Technology",
      "description": "For centuries, actuaries have been the backbone of insurance, using statistical models and risk assessment to shape the industry.",
      "type": "Panel",
      "speakers": []
    },
    {
      "day": "Day 2",
      "date": "October 15, 2025",
      "title": "Insurance M&A Trends",
      "startTime": "2025-10-15T14:00:00",
      "endTime": "2025-10-15T14:45:00",
      "location": "Executive Track",
      "track": "Strategy",
      "description": "The insurance industry's deal-making machine is in full swing, with strategic acquisitions, blockbuster mergers, and insurtech consolidations reshaping the landscape.",
      "type": "Panel",
      "speakers": []
    },
    {
      "day": "Day 2",
      "date": "October 15, 2025",
      "title": "Early Intervention in Health Insurance",
      "startTime": "2025-10-15T14:00:00",
      "endTime": "2025-10-15T14:45:00",
      "location": "Health Track",
      "track": "Health",
      "description": "Early intervention isn't just good medicine, it's good business. As healthcare costs surge, health insurers are redesigning plans to prioritize prevention.",
      "type": "Workshop",
      "speakers": []
    },
    {
      "day": "Day 2",
      "date": "October 15, 2025",
      "title": "ManyPets: Data-Driven Strategy",
      "startTime": "2025-10-15T15:00:00",
      "endTime": "2025-10-15T15:45:00",
      "location": "Technology Track",
      "track": "Technology",
      "description": "At ManyPets, data isn't just a function, it's a mindset. The CEO and Chief Data Officer share how they've embedded data at the heart of their strategy.",
      "type": "Case Study",
      "speakers": []
    },
    {
      "day": "Day 2",
      "date": "October 15, 2025",
      "title": "Lunch on Expo Floor",
      "startTime": "2025-10-15T12:00:00",
      "endTime": "2025-10-15T13:00:00",
      "location": "Expo Floor",
      "track": "Break",
      "description": "Explore grab-and-go lunch options right on the Expo Floor, join a curated lunch seminar for deeper insights, or discover the many wonders throughout the Expo.",
      "type": "Break",
      "speakers": []
    },
    {
      "day": "Day 2",
      "date": "October 15, 2025",
      "title": "Behavioral Insurance and Loss Prevention",
      "startTime": "2025-10-15T15:00:00",
      "endTime": "2025-10-15T15:45:00",
      "location": "Innovation Track",
      "track": "Innovation",
      "description": "The future of insurance isn't just about reacting to claims—it's about preventing losses, reducing friction, and building trust in real time.",
      "type": "Workshop",
      "speakers": []
    },
    {
      "day": "Day 2",
      "date": "October 15, 2025",
      "title": "Channel-First Insurance Design",
      "startTime": "2025-10-15T15:00:00",
      "endTime": "2025-10-15T15:45:00",
      "location": "Distribution Track",
      "track": "Distribution",
      "description": "Most insurers start with a product, then look for a channel. But what happens when you start with the channel — a brand with scale, user trust, and distribution built in.",
      "type": "Panel",
      "speakers": []
    },
    {
      "day": "Day 2",
      "date": "October 15, 2025",
      "title": "EOX Vantage Commercial Insurance Demo",
      "startTime": "2025-10-15T16:00:00",
      "endTime": "2025-10-15T16:30:00",
      "location": "Demo Theater",
      "track": "Technology",
      "description": "Commercial insurance is complex—submission volumes are high, requirements are rigorous. EOX Vantage simplifies this complexity.",
      "type": "Demo",
      "speakers": []
    },
    {
      "day": "Day 2",
      "date": "October 15, 2025",
      "title": "Convr AI Underwriting Demo",
      "startTime": "2025-10-15T16:30:00",
      "endTime": "2025-10-15T17:00:00",
      "location": "Demo Theater",
      "track": "Technology",
      "description": "Convr is a modularized AI underwriting, data, and intelligent document processing workbench that enriches and expedites commercial insurance.",
      "type": "Demo",
      "speakers": []
    },
    {
      "day": "Day 2",
      "date": "October 15, 2025",
      "title": "Expo Floor Happy Hour",
      "startTime": "2025-10-15T17:00:00",
      "endTime": "2025-10-15T19:00:00",
      "location": "Expo Floor",
      "track": "Networking",
      "description": "Unwind and connect at our Expo Floor Happy Hour! Experience a lively atmosphere featuring musical performances, engaging activations, a biergarten, and so much more.",
      "type": "Networking",
      "speakers": []
    },
    {
      "day": "Day 3",
      "date": "October 16, 2025",
      "title": "Expo Floor Opens",
      "startTime": "2025-10-16T08:00:00",
      "endTime": "2025-10-16T17:00:00",
      "location": "Expo Floor",
      "track": "Expo",
      "description": "The Expo Floor is your realm of innovation, where you'll connect with industry leaders, explore cutting-edge solutions, and form valuable partnerships.",
      "type": "Expo",
      "speakers": []
    },
    {
      "day": "Day 3",
      "date": "October 16, 2025",
      "title": "Trust in AI Risk Models",
      "startTime": "2025-10-16T09:00:00",
      "endTime": "2025-10-16T09:45:00",
      "location": "Technology Track",
      "track": "Technology",
      "description": "AI and advanced analytics are revolutionizing risk modeling, but there's one big problem—can insurers, regulators, and customers actually trust the outputs?",
      "type": "Panel",
      "speakers": []
    },
    {
      "day": "Day 3",
      "date": "October 16, 2025",
      "title": "Future of Broker-Carrier Partnerships",
      "startTime": "2025-10-16T09:00:00",
      "endTime": "2025-10-16T09:45:00",
      "location": "Distribution Track",
      "track": "Distribution",
      "description": "For decades, the broker-carrier partnership has been the backbone of insurance distribution. But as embedded insurance, digital MGAs, and direct-to-consumer platforms gain traction.",
      "type": "Panel",
      "speakers": []
    },
    {
      "day": "Day 3",
      "date": "October 16, 2025",
      "title": "Intelligent Automation in Claims",
      "startTime": "2025-10-16T09:00:00",
      "endTime": "2025-10-16T09:45:00",
      "location": "Claims Track",
      "track": "Claims",
      "description": "Manual processes continue to be a major bottleneck in the claim lifecycle, but modern tools can apply intelligent automation to help reduce leakage.",
      "type": "Workshop",
      "speakers": []
    },
    {
      "day": "Day 3",
      "date": "October 16, 2025",
      "title": "Agentic AI Digital Workforce",
      "startTime": "2025-10-16T10:00:00",
      "endTime": "2025-10-16T10:45:00",
      "location": "Technology Track",
      "track": "Technology",
      "description": "Agentic AI solutions are transforming insurance by creating a digital workforce that enables employees and customers to form meaningful relationships.",
      "type": "Panel",
      "speakers": []
    },
    {
      "day": "Day 3",
      "date": "October 16, 2025",
      "title": "AI vs Human in Commercial Underwriting",
      "startTime": "2025-10-16T10:00:00",
      "endTime": "2025-10-16T10:45:00",
      "location": "Commercial Track",
      "track": "Commercial",
      "description": "AI is advancing fast, but is it ready to take the wheel in complex commercial underwriting? Proponents argue that AI can process vast datasets, detect hidden risks.",
      "type": "Debate",
      "speakers": []
    },
    {
      "day": "Day 3",
      "date": "October 16, 2025",
      "title": "Life & Health Underwriting Revolution",
      "startTime": "2025-10-16T10:00:00",
      "endTime": "2025-10-16T10:45:00",
      "location": "Life & Health Track",
      "track": "Life & Health",
      "description": "The underwriting revolution is here, fueled by real-time data, AI, and shifting consumer expectations.",
      "type": "Panel",
      "speakers": []
    },
    {
      "day": "Day 3",
      "date": "October 16, 2025",
      "title": "Higson Product Configurator Demo",
      "startTime": "2025-10-16T11:00:00",
      "endTime": "2025-10-16T11:30:00",
      "location": "Demo Theater",
      "track": "Technology",
      "description": "Join us and discover how Higson (by Decerto) - the product configurator trusted by Allianz, Aviva, Sompo, and Gulf Insurance Group - shrinks change cycles from months to just days.",
      "type": "Demo",
      "speakers": []
    },
    {
      "day": "Day 3",
      "date": "October 16, 2025",
      "title": "AI-Powered Claims Adjusters",
      "startTime": "2025-10-16T11:00:00",
      "endTime": "2025-10-16T11:45:00",
      "location": "Claims Track",
      "track": "Claims",
      "description": "Despite all the talk of automation, human expertise is still at the heart of the claims process. But what if AI could make adjusters faster, smarter, and more effective?",
      "type": "Fireside Chat",
      "speakers": []
    },
    {
      "day": "Day 3",
      "date": "October 16, 2025",
      "title": "Digital-First Distribution Strategies",
      "startTime": "2025-10-16T11:00:00",
      "endTime": "2025-10-16T11:45:00",
      "location": "Distribution Track",
      "track": "Distribution",
      "description": "Forget outdated sales tactics—today's insurance buyers demand speed, simplicity, and relevance.",
      "type": "Workshop",
      "speakers": []
    },
    {
      "day": "Day 3",
      "date": "October 16, 2025",
      "title": "Flowable Agentic AI Platform",
      "startTime": "2025-10-16T11:30:00",
      "endTime": "2025-10-16T12:00:00",
      "location": "Demo Theater",
      "track": "Technology",
      "description": "Discover how one of the top 10 U.S. P&C insurers is reimagining its operational backbone using agentic AI and intelligent process orchestration.",
      "type": "Demo",
      "speakers": []
    },
    {
      "day": "Day 3",
      "date": "October 16, 2025",
      "title": "AI Agents in Life & Benefits",
      "startTime": "2025-10-16T12:00:00",
      "endTime": "2025-10-16T12:45:00",
      "location": "Life & Health Track",
      "track": "Life & Health",
      "description": "Life insurance, annuity, and group benefits carriers are deploying AI agents to revolutionize operations from policy administration to claims adjudication.",
      "type": "Panel",
      "speakers": []
    },
    {
      "day": "Day 3",
      "date": "October 16, 2025",
      "title": "First 100 Days of Customer Experience",
      "startTime": "2025-10-16T12:00:00",
      "endTime": "2025-10-16T12:45:00",
      "location": "Customer Experience Track",
      "track": "Customer Experience",
      "description": "The moment a customer buys a policy, the clock starts ticking. The first 100 days define whether they'll stay engaged—or start shopping for their next insurer.",
      "type": "Fireside Chat",
      "speakers": []
    },
    {
      "day": "Day 3",
      "date": "October 16, 2025",
      "title": "Claims Process Transformation",
      "startTime": "2025-10-16T13:00:00",
      "endTime": "2025-10-16T13:45:00",
      "location": "Claims Track",
      "track": "Claims",
      "description": "The claims process is being transformed like never before—AI-powered fraud detection, real-time data, and straight-through processing are making faster settlements a reality.",
      "type": "Panel",
      "speakers": []
    },
    {
      "day": "Day 3",
      "date": "October 16, 2025",
      "title": "Battle for Customer Loyalty",
      "startTime": "2025-10-16T13:00:00",
      "endTime": "2025-10-16T13:45:00",
      "location": "Customer Experience Track",
      "track": "Customer Experience",
      "description": "The battle for customer loyalty isn't just about price—it's about seamless integration, convenience, and ongoing value.",
      "type": "Panel",
      "speakers": []
    },
    {
      "day": "Day 3",
      "date": "October 16, 2025",
      "title": "Real-Time Risk Assessment",
      "startTime": "2025-10-16T13:00:00",
      "endTime": "2025-10-16T13:45:00",
      "location": "Technology Track",
      "track": "Technology",
      "description": "The old way of assessing risk—static data, annual updates, and one-size-fits-all pricing—is fading fast.",
      "type": "Workshop",
      "speakers": []
    },
    {
      "day": "Day 3",
      "date": "October 16, 2025",
      "title": "Embedded Insurance Success Factors",
      "startTime": "2025-10-16T14:00:00",
      "endTime": "2025-10-16T14:45:00",
      "location": "Distribution Track",
      "track": "Distribution",
      "description": "Embedded insurance is no longer a nice-to-have—it's a major growth driver. But for every success story, there are countless failed partnerships.",
      "type": "Panel",
      "speakers": []
    },
    {
      "day": "Day 3",
      "date": "October 16, 2025",
      "title": "Climate Tech Evolution",
      "startTime": "2025-10-16T14:00:00",
      "endTime": "2025-10-16T14:45:00",
      "location": "Innovation Track",
      "track": "Innovation",
      "description": "Climate tech in insurance has come a long way—what started as better catastrophe modeling has evolved into real-time risk prevention.",
      "type": "Panel",
      "speakers": []
    },
    {
      "day": "Day 3",
      "date": "October 16, 2025",
      "title": "Specialty Insurance Evolution",
      "startTime": "2025-10-16T14:00:00",
      "endTime": "2025-10-16T14:45:00",
      "location": "Specialty Track",
      "track": "Specialty",
      "description": "From cyber threats and climate extremes to parametric innovations, specialty insurance is evolving at breakneck speed.",
      "type": "Panel",
      "speakers": []
    },
    {
      "day": "Day 3",
      "date": "October 16, 2025",
      "title": "Financial Wellness Innovation",
      "startTime": "2025-10-16T14:00:00",
      "endTime": "2025-10-16T14:45:00",
      "location": "Benefits Track",
      "track": "Benefits",
      "description": "Financial wellness isn't just about savings goals or budgeting apps, it's about creating stability in a world of income volatility.",
      "type": "Workshop",
      "speakers": []
    },
    {
      "day": "Day 3",
      "date": "October 16, 2025",
      "title": "Hyland Content-Driven AI Demo",
      "startTime": "2025-10-16T15:00:00",
      "endTime": "2025-10-16T15:30:00",
      "location": "Demo Theater",
      "track": "Technology",
      "description": "Discover Hyland's Content-Driven Agentic Applications and how the power of AI helps insurance organizations transform enterprise content.",
      "type": "Demo",
      "speakers": []
    },
    {
      "day": "Day 3",
      "date": "October 16, 2025",
      "title": "Lunch on Expo Floor",
      "startTime": "2025-10-16T12:00:00",
      "endTime": "2025-10-16T13:00:00",
      "location": "Expo Floor",
      "track": "Break",
      "description": "Explore grab-and-go lunch options right on the Expo Floor, join a curated lunch seminar for deeper insights.",
      "type": "Break",
      "speakers": []
    },
    {
      "day": "Day 3",
      "date": "October 16, 2025",
      "title": "Cyber Insurance for SMEs",
      "startTime": "2025-10-16T15:00:00",
      "endTime": "2025-10-16T15:45:00",
      "location": "Cyber Track",
      "track": "Cyber",
      "description": "Cyber threats are escalating, yet many SMEs remain underinsured and vulnerable, often perceived as high-risk, low-reward clients by cyber insurers.",
      "type": "Panel",
      "speakers": []
    },
    {
      "day": "Day 3",
      "date": "October 16, 2025",
      "title": "Future of Risk Assessment",
      "startTime": "2025-10-16T15:00:00",
      "endTime": "2025-10-16T15:45:00",
      "location": "Technology Track",
      "track": "Technology",
      "description": "With automation, AI, and climate change, the world we live in is evolving at an ever-increasing rate.",
      "type": "Panel",
      "speakers": []
    },
    {
      "day": "Day 3",
      "date": "October 16, 2025",
      "title": "Evolving Group Insurance with Mike Estep",
      "startTime": "2025-10-16T15:00:00",
      "endTime": "2025-10-16T15:45:00",
      "location": "Benefits Track",
      "track": "Benefits",
      "description": "As workforce demographics and expectations evolve, traditional benefits packages may no longer suffice. Mike Estep explores how Prudential is adapting.",
      "type": "Keynote",
      "speakers": [
        {
          "name": "Mike Estep",
          "title": "",
          "company": "Prudential"
        }
      ]
    },
    {
      "day": "Day 3",
      "date": "October 16, 2025",
      "title": "Cyber Insurance Evolution Keynote",
      "startTime": "2025-10-16T16:00:00",
      "endTime": "2025-10-16T16:45:00",
      "location": "Main Stage",
      "track": "Cyber",
      "description": "As cyber threats escalate, insurers must continuously evolve to stay ahead. This keynote will explore how cyber insurance is adapting to an era of perpetual risk.",
      "type": "Keynote",
      "speakers": []
    },
    {
      "day": "Day 3",
      "date": "October 16, 2025",
      "title": "Portable Benefits for Gig Economy",
      "startTime": "2025-10-16T16:00:00",
      "endTime": "2025-10-16T16:45:00",
      "location": "Benefits Track",
      "track": "Benefits",
      "description": "The traditional employer-anchored benefits model is being challenged by the rise of freelance, contract, and gig work.",
      "type": "Panel",
      "speakers": []
    },
    {
      "day": "Day 3",
      "date": "October 16, 2025",
      "title": "AI in Cyber Risk Quantification",
      "startTime": "2025-10-16T16:00:00",
      "endTime": "2025-10-16T16:45:00",
      "location": "Cyber Track",
      "track": "Cyber",
      "description": "Cyber risk is notoriously difficult to quantify, yet accurate pricing is crucial for sustainable insurance models.",
      "type": "Workshop",
      "speakers": []
    },
    {
      "day": "Day 3",
      "date": "October 16, 2025",
      "title": "Final Expo Floor Happy Hour",
      "startTime": "2025-10-16T17:00:00",
      "endTime": "2025-10-16T19:00:00",
      "location": "Expo Floor",
      "track": "Networking",
      "description": "This is your final time to walk and enjoy the Expo Floor at ITC Vegas! Make it count by experiencing a lively atmosphere featuring musical performances.",
      "type": "Networking",
      "speakers": []
    },
    {
      "day": "Day 3",
      "date": "October 16, 2025",
      "title": "Closing Party",
      "startTime": "2025-10-16T20:00:00",
      "endTime": "2025-10-16T23:00:00",
      "location": "Main Venue",
      "track": "Networking",
      "description": "You came, you saw, and you conquered ITC Vegas. Now, experience not just an epic and star-powered finish to the non-stop action.",
      "type": "Party",
      "speakers": []
    }
  ]
}